klogftp/HRMISPasswordTool.py
klogftp/__init__.py
klogftp/database.py
klogftp/dataframe_process.py
klogftp/hrapi.py
klogftp/kid_logger_file_arrange.py
klogftp/log.py
klogftp/portal.py
klogktp/HRMISPasswordTool.py
klogktp/__init__.py
klogktp/database.py
klogktp/dataframe_process.py
klogktp/hrapi.py
klogktp/kid_logger_file_arrange.py
klogktp/log.py
klogktp/portal.py
klogftp-0.0.4.dist-info/METADATA
klogftp-0.0.4.dist-info/WHEEL
klogftp-0.0.4.dist-info/license.txt
klogftp-0.0.4.dist-info/top_level.txt
klogftp-0.0.4.dist-info/RECORD
