Metadata-Version: 2.1
Name: klogftp
Version: 0.0.4
Summary: This is a package for Klog.
Home-page: https://github.com/pypa/sampleproject
Author: JasonWu
Author-email: wujason0509@gmail.com
License: UNKNOWN
Platform: UNKNOWN
Classifier: Programming Language :: Python :: 3
Classifier: License :: OSI Approved :: MIT License
Classifier: Operating System :: OS Independent
Requires-Python: >=3.7
